{
  "$schema": "https://developer.microsoft.com/json-schemas/fabric/item/report/definition/visualContainer/2.4.0/schema.json",
  "name": "2157f4a84a06773de4c2",
  "position": {
    "x": 988.57142857142867,
    "y": 225.71428571428572,
    "z": 2000,
    "height": 134.28571428571431,
    "width": 245.71428571428572,
    "tabOrder": 2000
  },
  "visual": {
    "visualType": "gauge",
    "query": {
      "queryState": {
        "TargetValue": {
          "projections": [
            {
              "field": {
                "Measure": {
                  "Expression": {
                    "SourceRef": {
                      "Entity": "Stats_playoff_pergame_joueurs_NBA"
                    }
                  },
                  "Property": "BLK Équipe Sélectionnée"
                }
              },
              "queryRef": "Stats_playoff_pergame_joueurs_NBA.BLK Équipe Sélectionnée",
              "nativeQueryRef": "BLK Équipe Sélectionnée"
            }
          ]
        },
        "Y": {
          "projections": [
            {
              "field": {
                "Measure": {
                  "Expression": {
                    "SourceRef": {
                      "Entity": "Stats_playoff_pergame_joueurs_NBA"
                    }
                  },
                  "Property": "BLK_Team"
                }
              },
              "queryRef": "Stats_playoff_pergame_joueurs_NBA.BLK_Team",
              "nativeQueryRef": "BLK_Team"
            }
          ]
        }
      },
      "sortDefinition": {
        "sort": [
          {
            "field": {
              "Measure": {
                "Expression": {
                  "SourceRef": {
                    "Entity": "Stats_playoff_pergame_joueurs_NBA"
                  }
                },
                "Property": "BLK_Team"
              }
            },
            "direction": "Descending"
          }
        ],
        "isDefaultSort": true
      }
    },
    "objects": {
      "dataPoint": [
        {
          "properties": {
            "target": {
              "solid": {
                "color": {
                  "expr": {
                    "Measure": {
                      "Expression": {
                        "SourceRef": {
                          "Entity": "Stats_playoff_pergame_joueurs_NBA"
                        }
                      },
                      "Property": "Couleur_Équipe_Secondaire"
                    }
                  }
                }
              }
            },
            "fill": {
              "solid": {
                "color": {
                  "expr": {
                    "Measure": {
                      "Expression": {
                        "SourceRef": {
                          "Entity": "Stats_playoff_pergame_joueurs_NBA"
                        }
                      },
                      "Property": "Couleur_Équipe"
                    }
                  }
                }
              }
            }
          }
        }
      ],
      "labels": [
        {
          "properties": {
            "fontSize": {
              "expr": {
                "Literal": {
                  "Value": "10D"
                }
              }
            }
          }
        }
      ],
      "axis": [
        {
          "properties": {}
        }
      ],
      "calloutValue": [
        {
          "properties": {
            "show": {
              "expr": {
                "Literal": {
                  "Value": "true"
                }
              }
            }
          }
        }
      ]
    },
    "visualContainerObjects": {
      "border": [
        {
          "properties": {
            "show": {
              "expr": {
                "Literal": {
                  "Value": "false"
                }
              }
            }
          }
        }
      ],
      "dropShadow": [
        {
          "properties": {
            "show": {
              "expr": {
                "Literal": {
                  "Value": "true"
                }
              }
            },
            "color": {
              "solid": {
                "color": {
                  "expr": {
                    "Measure": {
                      "Expression": {
                        "SourceRef": {
                          "Entity": "Stats_playoff_pergame_joueurs_NBA"
                        }
                      },
                      "Property": "Couleur_Équipe"
                    }
                  }
                }
              }
            },
            "preset": {
              "expr": {
                "Literal": {
                  "Value": "'Center'"
                }
              }
            },
            "angle": {
              "expr": {
                "Literal": {
                  "Value": "0L"
                }
              }
            },
            "shadowDistance": {
              "expr": {
                "Literal": {
                  "Value": "0L"
                }
              }
            },
            "shadowBlur": {
              "expr": {
                "Literal": {
                  "Value": "15L"
                }
              }
            },
            "shadowSpread": {
              "expr": {
                "Literal": {
                  "Value": "3L"
                }
              }
            },
            "transparency": {
              "expr": {
                "Literal": {
                  "Value": "70L"
                }
              }
            }
          }
        }
      ],
      "background": [
        {
          "properties": {
            "transparency": {
              "expr": {
                "Literal": {
                  "Value": "82D"
                }
              }
            }
          }
        }
      ],
      "title": [
        {
          "properties": {
            "text": {
              "expr": {
                "Measure": {
                  "Expression": {
                    "SourceRef": {
                      "Entity": "Stats_playoff_pergame_joueurs_NBA"
                    }
                  },
                  "Property": "_TitreBLK"
                }
              }
            }
          }
        }
      ]
    },
    "drillFilterOtherVisuals": true
  }
}