{
  "$schema": "https://developer.microsoft.com/json-schemas/fabric/item/report/definition/visualContainer/2.4.0/schema.json",
  "name": "f806bec21a15dce15e25",
  "position": {
    "x": 12.857142857142858,
    "y": 254.28571428571431,
    "z": 4000,
    "height": 158.57142857142858,
    "width": 330,
    "tabOrder": 4000
  },
  "visual": {
    "visualType": "donutChart",
    "query": {
      "queryState": {
        "Y": {
          "projections": [
            {
              "field": {
                "Aggregation": {
                  "Expression": {
                    "Column": {
                      "Expression": {
                        "SourceRef": {
                          "Entity": "Stats_NCAA"
                        }
                      },
                      "Property": "AST"
                    }
                  },
                  "Function": 1
                }
              },
              "queryRef": "Sum(Stats_NCAA.AST)",
              "nativeQueryRef": "AST NCAA",
              "displayName": "AST NCAA"
            },
            {
              "field": {
                "Aggregation": {
                  "Expression": {
                    "Column": {
                      "Expression": {
                        "SourceRef": {
                          "Entity": "stats_saisonreguliere_par_match_joueur"
                        }
                      },
                      "Property": "AST"
                    }
                  },
                  "Function": 1
                }
              },
              "queryRef": "Sum(stats_saisonreguliere_par_match_joueur.AST)",
              "nativeQueryRef": "AST NBA",
              "displayName": "AST NBA"
            }
          ]
        }
      },
      "sortDefinition": {
        "sort": [
          {
            "field": {
              "Aggregation": {
                "Expression": {
                  "Column": {
                    "Expression": {
                      "SourceRef": {
                        "Entity": "Stats_NCAA"
                      }
                    },
                    "Property": "AST"
                  }
                },
                "Function": 1
              }
            },
            "direction": "Descending"
          }
        ],
        "isDefaultSort": true
      }
    },
    "objects": {
      "legend": [
        {
          "properties": {
            "show": {
              "expr": {
                "Literal": {
                  "Value": "true"
                }
              }
            }
          }
        }
      ],
      "labels": [
        {
          "properties": {
            "show": {
              "expr": {
                "Literal": {
                  "Value": "true"
                }
              }
            },
            "position": {
              "expr": {
                "Literal": {
                  "Value": "'outside'"
                }
              }
            },
            "overflow": {
              "expr": {
                "Literal": {
                  "Value": "true"
                }
              }
            },
            "labelStyle": {
              "expr": {
                "Literal": {
                  "Value": "'Data'"
                }
              }
            },
            "labelDisplayUnits": {
              "expr": {
                "Literal": {
                  "Value": "0D"
                }
              }
            },
            "labelPrecision": {
              "expr": {
                "Literal": {
                  "Value": "2L"
                }
              }
            }
          }
        }
      ],
      "slices": [
        {
          "properties": {
            "startAngle": {
              "expr": {
                "Literal": {
                  "Value": "20L"
                }
              }
            }
          }
        }
      ],
      "dataPoint": [
        {
          "properties": {
            "fill": {
              "solid": {
                "color": {
                  "expr": {
                    "Literal": {
                      "Value": "'#007ADD'"
                    }
                  }
                }
              }
            }
          },
          "selector": {
            "metadata": "Sum(Stats_NCAA.AST)"
          }
        },
        {
          "properties": {
            "fill": {
              "solid": {
                "color": {
                  "expr": {
                    "Literal": {
                      "Value": "'#C80F2E'"
                    }
                  }
                }
              }
            }
          },
          "selector": {
            "metadata": "Sum(stats_saisonreguliere_par_match_joueur.AST)"
          }
        }
      ]
    },
    "visualContainerObjects": {
      "background": [
        {
          "properties": {
            "show": {
              "expr": {
                "Literal": {
                  "Value": "true"
                }
              }
            }
          }
        }
      ],
      "title": [
        {
          "properties": {
            "text": {
              "expr": {
                "Literal": {
                  "Value": "'AST'"
                }
              }
            },
            "alignment": {
              "expr": {
                "Literal": {
                  "Value": "'center'"
                }
              }
            }
          }
        }
      ],
      "border": [
        {
          "properties": {
            "show": {
              "expr": {
                "Literal": {
                  "Value": "true"
                }
              }
            }
          }
        }
      ],
      "dropShadow": [
        {
          "properties": {
            "show": {
              "expr": {
                "Literal": {
                  "Value": "false"
                }
              }
            },
            "position": {
              "expr": {
                "Literal": {
                  "Value": "'Outer'"
                }
              }
            },
            "preset": {
              "expr": {
                "Literal": {
                  "Value": "'CenterLeft'"
                }
              }
            },
            "angle": {
              "expr": {
                "Literal": {
                  "Value": "180L"
                }
              }
            },
            "shadowDistance": {
              "expr": {
                "Literal": {
                  "Value": "10L"
                }
              }
            },
            "shadowBlur": {
              "expr": {
                "Literal": {
                  "Value": "10L"
                }
              }
            },
            "shadowSpread": {
              "expr": {
                "Literal": {
                  "Value": "3L"
                }
              }
            },
            "transparency": {
              "expr": {
                "Literal": {
                  "Value": "70L"
                }
              }
            },
            "color": {
              "solid": {
                "color": {
                  "expr": {
                    "ThemeDataColor": {
                      "ColorId": 2,
                      "Percent": 0
                    }
                  }
                }
              }
            }
          }
        }
      ],
      "visualTooltip": [
        {
          "properties": {
            "show": {
              "expr": {
                "Literal": {
                  "Value": "false"
                }
              }
            }
          }
        }
      ]
    },
    "drillFilterOtherVisuals": true
  }
}